{
  "pools": [
    {
      "name": "forestry_factory_items",
      "rolls": 1,
      "entries": [
        {
          "type": "item",
          "name": "forestry:broken_bronze_shovel",
          "weight": 10
        },
        {
          "type": "item",
          "name": "forestry:broken_bronze_pickaxe",
          "weight": 30
        },
        {
          "type": "item",
          "name": "forestry:kit_pickaxe",
          "weight": 10
        },
        {
          "type": "item",
          "name": "forestry:kit_shovel",
          "weight": 5
        },
        {
          "type": "empty",
          "weight": 50
        }
      ]
    }
  ]
}
