{
  "type": "forge:conditional",
  "recipes": [
    {
      "conditions": [
        {
          "module": "arboriculture",
          "container": "forestry",
          "type": "forestry:module"
        }
      ],
      "recipe": {
        "type": "minecraft:crafting_shaped",
        "pattern": [
          "  B",
          " # ",
          "#  "
        ],
        "key": {
          "B": {
            "tag": "forge:ingots/bronze"
          },
          "#": {
            "tag": "forge:rods/wooden"
          }
        },
        "result": {
          "item": "forestry:grafter"
        }
      }
    }
  ]
}