{
  "type": "forge:conditional",
  "recipes": [
    {
      "conditions": [
        {
          "module": "worktable",
          "container": "forestry",
          "type": "forestry:module"
        }
      ],
      "recipe": {
        "type": "minecraft:crafting_shaped",
        "pattern": [
          "B",
          "W",
          "C"
        ],
        "key": {
          "B": {
            "item": "minecraft:book"
          },
          "C": {
            "tag": "forge:chests/wooden"
          },
          "W": {
            "item": "minecraft:crafting_table"
          }
        },
        "result": {
          "item": "forestry:worktable"
        }
      }
    }
  ]
}